gmfy/__init__.py
gmfy/async_clients/__init__.py
gmfy/async_clients/api_client.py
gmfy/async_clients/gmfy_client.py
gmfy/base_api_client.py
gmfy/base_events.py
gmfy/base_payment.py
gmfy/config.py
gmfy/constants.py
gmfy/data.py
gmfy/event_managers.py
gmfy/exceptions.py
gmfy/sync_clients/__init__.py
gmfy/sync_clients/api_client.py
gmfy/sync_clients/gmfy_client.py
gmfy/utils.py
gmfy-0.0.4.dist-info/METADATA
gmfy-0.0.4.dist-info/WHEEL
gmfy-0.0.4.dist-info/RECORD
