Metadata-Version: 2.1
Name: gmfy
Version: 0.0.4
Summary: This is a simple library for working with the gmfy api.
Keywords: gmfy API gamification
Author: Evgeny Izvekov
Author-email: evgeny.izvekov@redcollar.ru
Requires-Python: >=3.12,<4.0
Classifier: Development Status :: 3 - Alpha
Classifier: Intended Audience :: Developers
Classifier: License :: OSI Approved :: MIT License
Classifier: Operating System :: MacOS
Classifier: Programming Language :: Python :: 3
Classifier: Programming Language :: Python :: 3.12
Provides-Extra: async
Provides-Extra: sync
Requires-Dist: httpx (>=0.27.0,<0.28.0) ; extra == "async"
Requires-Dist: pydantic (>=2.8.2,<3.0.0)
Requires-Dist: requests (>=2.32.3,<3.0.0) ; extra == "sync"
Project-URL: Docs, https://pypi.org/project/gmfy/
